{"innerCode":200,"data":{"size":"m-size","name":"HPSM Update Entry","description":"Update entry.","Timeout":"00:01:00","class":[],"rootSettings":{"isCollapse":false,"activitySettings":[{"value":"","disabled":false,"required":true,"key":"SelectedModuleName","idFieldName":"SelectedModuleID","label":"Module Name","labelKey":"","styleClass":"one-line","baseType":"control","controlType":"dropdown","autocompleteParams":{"extraParams":21,"entityType":36},"controlOptions":[]},{"value":"","required":true,"disabled":false,"key":"FormName_UI","idFieldName":"FormId","label":"Form Name","labelKey":"","styleClass":"","baseType":"control","controlType":"autocomplete","controlOptions":[],"additionalParams":{"dependentFields":["Action"]}},{"value":"","required":true,"key":"Action","label":"Action","labelKey":"ACTION","baseType":"control","controlType":"autocomplete","controlOptions":[]},{"value":"","key":"FormName","baseType":"control","controlType":"hidden"},{"isCollapse":true,"isVisible":true,"styleClass":["formGroup"],"key":"properties","label":"Properties","labelKey":"PROPERTIES","baseType":"group","activitySettings":[{"value":"","disabled":false,"required":true,"key":"XMLTableResult","specialFieldType":"isKeyField","initialFormFields":{"IncidentManagement(Incident)":{"JournalUpdates":true},"ProblemManagement(Problem)":{"update":true}},"label":"","labelKey":"","styleClass":"one-line","baseType":"control","controlType":"propertiesControl","containsPrimaryKey":true,"controlOptions":[]}]}],"index":"1","label":"main","labelKey":null}},"message":"SUCCESS"}