{"data":{"name":"Multi SSH Commands","description":"Runs multi SSH commands.","Timeout":"00:01:00","size":"m-size","class":[],"rootSettings":{"isCollapse":false,"activitySettings":[{"value":"","required":true,"key":"Comm","disabled":false,"styleClass":"","label":"Command","labelKey":"MULTI_SSH_COMMANDS_COMMAND","baseType":"control","controlType":"textarea","controlOptions":[]},{"value":"22","required":true,"key":"Port","disabled":false,"styleClass":"","label":"Port","labelKey":"MULTI_SSH_COMMANDS_PORT","baseType":"control","controlType":"textbox","controlOptions":[]},{"value":"","required":false,"key":"hostGroup1","disabled":false,"label":"new control11","styleClass":"","labelKey":"","baseType":"hostGroup","controlType":"","controlOptions":[]},{"value":"","key":"certtype","label":"Certification Type","styleClass":"","labelKey":"CERTIFICATION_TYPE","baseType":"control","controlType":"dropdown","controlOptions":[{"key":"None","value":"None"},{"key":"Kerberos","value":"Kerberos"},{"key":"PEM","value":"PEM"},{"key":"PKI","value":"PKI"},{"key":"PPK","value":"PPK"}]},{"value":"","key":"certpath","label":"Certification Path","styleClass":"","labelKey":"CERTIFICATION_PATH","baseType":"control","controlType":"textbox","controlOptions":[]},{"value":"0","required":true,"key":"OSType","disabled":false,"styleClass":"","label":"","labelKey":"","baseType":"control","controlType":"hidden"}],"index":"1","label":"main","labelKey":null}}}